nedoc/__init__.py
nedoc/__main__.py
nedoc/cmd.py
nedoc/config.py
nedoc/core.py
nedoc/docstring.py
nedoc/parse.py
nedoc/render.py
nedoc/rst.py
nedoc/unit.py
nedoc/utils.py
nedoc/version.py
nedoc/templates/base.mako
nedoc/templates/class.mako
nedoc/templates/docstring.mako
nedoc/templates/function.mako
nedoc/templates/module.mako
nedoc/templates/nedoc.js
nedoc/templates/source.mako
nedoc/templates/utils.mako
nedoc/templates/assets/style.css
nedoc/templates/assets/jquery/jquery-3.0.0.min.js
nedoc/templates/assets/jquery/jquery-ui.min.css
nedoc/templates/assets/jquery/jquery-ui.min.js
nedoc/templates/assets/purecss/LICENSE
nedoc/templates/assets/purecss/grids-responsive-min.css
nedoc/templates/assets/purecss/pure-min.css
nedoc/templates/assets/pygments/default.css
nedoc-0.10.dist-info/LICENSE
nedoc-0.10.dist-info/METADATA
nedoc-0.10.dist-info/WHEEL
nedoc-0.10.dist-info/top_level.txt
nedoc-0.10.dist-info/RECORD
