Metadata-Version: 2.1
Name: nedoc
Version: 0.10
Summary: Generator for API documentation
Home-page: https://github.com/spirali/nedoc
Author: Stanislav Bohm
Author-email: spirali@kreatrix.org
License: MIT
Platform: UNKNOWN
Provides: nedoc
Requires-Dist: asttokens (==2.0.5)
Requires-Dist: docstring-parser (==0.13)
Requires-Dist: docutils (==0.18.1)
Requires-Dist: htmlmin (==0.1.12)
Requires-Dist: mako (==1.1.6)
Requires-Dist: pygments (==2.11.2)
Requires-Dist: tqdm (==4.62.3)
